corpusflow/__init__.py
corpusflow/__init__.py.bak.py
corpusflow/analysis/__init__.py
corpusflow/analysis/express_pattern/__init__.py
corpusflow/augmentor/__init__.py
corpusflow/augmentor/back_translate/__init__.py
corpusflow/augmentor/back_translate/back_translate_augmentor.py
corpusflow/augmentor/back_translate/apis/__init__.py
corpusflow/augmentor/back_translate/apis/baidu_cloud_translate.py
corpusflow/augmentor/back_translate/apis/baidu_lang_code.py
corpusflow/augmentor/back_translate/apis/base_translate.py
corpusflow/augmentor/back_translate/apis/google_cloud_translate.py
corpusflow/augmentor/back_translate/apis/google_lang_code.py
corpusflow/augmentor/back_translate/apis/microsoft_cloud_translate.py
corpusflow/augmentor/back_translate/apis/microsoft_lang_code.py
corpusflow/augmentor/eda/__init__.py
corpusflow/augmentor/eda/eda_augmenter.py
corpusflow/augmentor/eda/random_delete.py
corpusflow/augmentor/eda/random_insert.py
corpusflow/augmentor/eda/random_swap.py
corpusflow/augmentor/eda/synonym_replace.py
corpusflow/augmentor/stopwords/__init__.py
corpusflow/augmentor/stopwords/text_based_stopwords.py
corpusflow/core/__init__.py
corpusflow/generate/__init__.py
corpusflow/io/__init__.py
corpusflow/io/markdown/__init__.py
corpusflow/io/markdown/read_markdown.py
corpusflow-0.2.0.dist-info/AUTHORS.rst
corpusflow-0.2.0.dist-info/LICENSE
corpusflow-0.2.0.dist-info/METADATA
corpusflow-0.2.0.dist-info/WHEEL
corpusflow-0.2.0.dist-info/top_level.txt
corpusflow-0.2.0.dist-info/RECORD
