Metadata-Version: 2.1
Name: corpusflow
Version: 0.2.0
Summary: CorpusFlow is an open source platform for Neural Language Processing. It has a comprehensive, flexible ecosystem of tools, libraries and community resources that lets researchers push the state-of-the-art in NLP and developers easily build and deploy NLP powered applications.
Home-page: https://github.com/howl-anderson/corpusflow
Author: Xiaoquan Kong
Author-email: u1mail2me@gmail.com
License: MIT license
Keywords: corpusflow
Platform: UNKNOWN
Classifier: Development Status :: 2 - Pre-Alpha
Classifier: Intended Audience :: Developers
Classifier: License :: OSI Approved :: MIT License
Classifier: Natural Language :: English
Classifier: Programming Language :: Python :: 3
Classifier: Programming Language :: Python :: 3.5
Classifier: Programming Language :: Python :: 3.6
Classifier: Programming Language :: Python :: 3.7
Classifier: Programming Language :: Python :: 3.8
Requires-Python: >=3.5
Requires-Dist: numpy
Requires-Dist: google-cloud-translate
Requires-Dist: requests
Requires-Dist: micro-toolkit
Requires-Dist: tenacity
Requires-Dist: tokenizer-tools
Requires-Dist: mistletoe
